[
  {
    "id": 1,
    "title": "Inception",
    "year": 2010,
    "genre": ["Action", "Sci-Fi", "Thriller"],
    "director": "Christopher Nolan",
    "cast": ["Leonardo DiCaprio", "Joseph Gordon-Levitt", "Elliot Page", "Tom Hardy"],
    "duration_minutes": 148,
    "rating": "PG-13",
    "imdb_score": 8.8,
    "language": "English",
    "country": "USA",
    "box_office_usd": 836848102,
    "synopsis": "A thief who steals corporate secrets through dream-sharing technology is given the inverse task of planting an idea into the mind of a C.E.O.",
    "poster_url": "https://example.com/posters/inception.jpg",
    "available_on": ["Netflix", "HBO Max"]
  },
  {
    "id": 2,
    "title": "Parasite",
    "year": 2019,
    "genre": ["Drama", "Thriller", "Comedy"],
    "director": "Bong Joon-ho",
    "cast": ["Song Kang-ho", "Lee Sun-kyun", "Cho Yeo-jeong", "Choi Woo-shik"],
    "duration_minutes": 132,
    "rating": "R",
    "imdb_score": 8.5,
    "language": "Korean",
    "country": "South Korea",
    "box_office_usd": 258773645,
    "synopsis": "A poor family schemes to become employed by a wealthy family and infiltrate their household by posing as unrelated, highly qualified individuals.",
    "poster_url": "https://example.com/posters/parasite.jpg",
    "available_on": ["Hulu", "Amazon Prime"]
  },
  {
    "id": 3,
    "title": "The Grand Budapest Hotel",
    "year": 2014,
    "genre": ["Comedy", "Drama", "Adventure"],
    "director": "Wes Anderson",
    "cast": ["Ralph Fiennes", "Tony Revolori", "Saoirse Ronan", "Bill Murray"],
    "duration_minutes": 99,
    "rating": "R",
    "imdb_score": 8.1,
    "language": "English",
    "country": "USA",
    "box_office_usd": 174800000,
    "synopsis": "The adventures of Gustave H, a legendary concierge at a famous European hotel between the wars, and Zero Moustafa, the lobby boy who becomes his most trusted friend.",
    "poster_url": "https://example.com/posters/grand-budapest-hotel.jpg",
    "available_on": ["Disney+", "Amazon Prime"]
  },
  {
    "id": 4,
    "title": "Interstellar",
    "year": 2014,
    "genre": ["Adventure", "Drama", "Sci-Fi"],
    "director": "Christopher Nolan",
    "cast": ["Matthew McConaughey", "Anne Hathaway", "Jessica Chastain", "Michael Caine"],
    "duration_minutes": 169,
    "rating": "PG-13",
    "imdb_score": 8.7,
    "language": "English",
    "country": "USA",
    "box_office_usd": 701729206,
    "synopsis": "A team of explorers travel through a wormhole in space in an attempt to ensure humanity's survival as Earth faces an environmental collapse.",
    "poster_url": "https://example.com/posters/interstellar.jpg",
    "available_on": ["Paramount+", "Netflix"]
  },
  {
    "id": 5,
    "title": "Amélie",
    "year": 2001,
    "genre": ["Romance", "Comedy", "Drama"],
    "director": "Jean-Pierre Jeunet",
    "cast": ["Audrey Tautou", "Mathieu Kassovitz", "Rufus", "Lorella Cravotta"],
    "duration_minutes": 122,
    "rating": "R",
    "imdb_score": 8.3,
    "language": "French",
    "country": "France",
    "box_office_usd": 174200000,
    "synopsis": "Amélie is an innocent and naive girl in Paris with her own sense of justice, who decides to help those around her and, in doing so, discovers love.",
    "poster_url": "https://example.com/posters/amelie.jpg",
    "available_on": ["Mubi", "Amazon Prime"]
  },
  {
    "id": 6,
    "title": "The Dark Knight",
    "year": 2008,
    "genre": ["Action", "Crime", "Drama"],
    "director": "Christopher Nolan",
    "cast": ["Christian Bale", "Heath Ledger", "Aaron Eckhart", "Maggie Gyllenhaal"],
    "duration_minutes": 152,
    "rating": "PG-13",
    "imdb_score": 9.0,
    "language": "English",
    "country": "USA",
    "box_office_usd": 1004558444,
    "synopsis": "When the menace known as the Joker wreaks havoc and chaos on the people of Gotham, Batman must accept one of the greatest psychological and physical tests of his ability to fight injustice.",
    "poster_url": "https://example.com/posters/dark-knight.jpg",
    "available_on": ["HBO Max"]
  },
  {
    "id": 7,
    "title": "Spirited Away",
    "year": 2001,
    "genre": ["Animation", "Adventure", "Family"],
    "director": "Hayao Miyazaki",
    "cast": ["Daveigh Chase", "Suzanne Pleshette", "Miyu Irino", "Rumi Hiiragi"],
    "duration_minutes": 125,
    "rating": "PG",
    "imdb_score": 8.6,
    "language": "Japanese",
    "country": "Japan",
    "box_office_usd": 395802150,
    "synopsis": "During her family's move to the suburbs, a sullen 10-year-old girl wanders into a world ruled by gods, witches, and spirits, and where humans are changed into beasts.",
    "poster_url": "https://example.com/posters/spirited-away.jpg",
    "available_on": ["Netflix", "HBO Max"]
  },
  {
    "id": 8,
    "title": "Mad Max: Fury Road",
    "year": 2015,
    "genre": ["Action", "Adventure", "Sci-Fi"],
    "director": "George Miller",
    "cast": ["Tom Hardy", "Charlize Theron", "Nicholas Hoult", "Hugh Keays-Byrne"],
    "duration_minutes": 120,
    "rating": "R",
    "imdb_score": 8.1,
    "language": "English",
    "country": "Australia",
    "box_office_usd": 375436354,
    "synopsis": "In a post-apocalyptic wasteland, a woman rebels against a tyrannical ruler in search for her homeland with the aid of a group of female prisoners and a drifter named Max.",
    "poster_url": "https://example.com/posters/mad-max-fury-road.jpg",
    "available_on": ["Netflix", "Amazon Prime"]
  },
  {
    "id": 9,
    "title": "Coco",
    "year": 2017,
    "genre": ["Animation", "Adventure", "Family"],
    "director": "Lee Unkrich",
    "cast": ["Anthony Gonzalez", "Gael García Bernal", "Benjamin Bratt", "Alanna Ubach"],
    "duration_minutes": 105,
    "rating": "PG",
    "imdb_score": 8.4,
    "language": "English",
    "country": "USA",
    "box_office_usd": 807082196,
    "synopsis": "Aspiring musician Miguel, confronted with his family's ancestral ban on music, enters the Land of the Dead to find his great-great-grandfather, a legendary singer.",
    "poster_url": "https://example.com/posters/coco.jpg",
    "available_on": ["Disney+"]
  },
  {
    "id": 10,
    "title": "Oldboy",
    "year": 2003,
    "genre": ["Mystery", "Thriller", "Drama"],
    "director": "Park Chan-wook",
    "cast": ["Choi Min-sik", "Yoo Ji-tae", "Gang Hye-jung", "Kim Byeong-ok"],
    "duration_minutes": 120,
    "rating": "R",
    "imdb_score": 8.4,
    "language": "Korean",
    "country": "South Korea",
    "box_office_usd": 15000000,
    "synopsis": "After being kidnapped and imprisoned for fifteen years without any explanation, a man is released and given five days to find his captor.",
    "poster_url": "https://example.com/posters/oldboy.jpg",
    "available_on": ["Mubi", "Shudder"]
  }
]
